{"cameraMode":{"drawMode":0,"name":"Shaded","section":"Shading Mode"},"sceneLighting":true,"audioPlay":false,"sceneViewState":{"showFog":true,"showMaterialUpdate":false,"showSkybox":true,"showFlares":true,"showImageEffects":true,"showParticleSystems":true},"in2DMode":false,"pivot":{"x":102.28214263916016,"y":83.59232330322266,"z":12.472625732421875},"rotation":{"x":0.01230914331972599,"y":-0.0000042849042074522,"z":0.0000051089659791614398,"w":0.9999294877052307},"size":152.6958770751953,"orthographic":false}